[
  {
    "version": "3.0.7.2",
    "changelog": "Fix mixin",
    "type": "release"
  },{
    "version": "3.0.7.1",
    "changelog": "Fix mc version",
    "type": "release"
  },{
    "version": "3.0.7",
    "changelog": "Fixed more bugs\nAdded a /discord rawmsg command\nAdded whitelist option for commandlog",
    "type": "release"
  },{
    "version": "3.0.6",
    "changelog": "Implemented a few bug fixes\nAdd more events for addon developers",
    "type": "release"
  },{
    "version": "3.0.5",
    "changelog": "Fix server stopping not working\nFix update checker\nImplement URL Encoded advancement message\nImplement permissions",
    "type": "beta"
  },{
    "version": "3.0.3",
    "changelog": "Added custom status\nAdded tellraw\nAdded option to disable chat message editing for compatibility reasons\nFixed lots of bugs",
    "type": "beta"
  },
  {
    "version": "3.0.2",
    "changelog": "Fixed linking not being saved\nOptimized code",
    "type": "alpha"
  }
]